rf_calc.py
rf_calc-0.0.7.dist-info/METADATA
rf_calc-0.0.7.dist-info/WHEEL
rf_calc-0.0.7.dist-info/top_level.txt
rf_calc-0.0.7.dist-info/RECORD
