Metadata-Version: 2.1
Name: rf-calc
Version: 0.0.7
Summary: Often we spend lots of time calculating the Receptive field of a CNN model.This Module can calculate the receptive field, Output image size  from a model object
Home-page: UNKNOWN
Author: Pruthiraj Jayasingh
Author-email: pruthirajjayasingh.4u@gmail.com
License: UNKNOWN
Platform: UNKNOWN
Classifier: Programming Language :: Python :: 3
Classifier: Programming Language :: Python :: 3.6
Classifier: Programming Language :: Python :: 3.7
Classifier: Programming Language :: Python :: 3.8
Classifier: License :: OSI Approved :: GNU General Public License v2 or later (GPLv2+)
Classifier: Operating System :: OS Independent
Requires-Dist: numpy (>=1.19.4)
Requires-Dist: pandas (>=1.1.5)
Requires-Dist: tabulate (>=0.8.9)
